Metadata-Version: 2.1
Name: clitoo
Version: 1.0.3.dev6
Summary: execute python callables from CLI too !
Home-page: https://yourlabs.io/oss/clitoo
Author: James Pic
Author-email: jamespic@gmail.com
License: MIT
Keywords: cli
Platform: UNKNOWN
Classifier: Development Status :: 5 - Production/Stable
Classifier: Environment :: Console
Classifier: Environment :: Plugins
Classifier: Intended Audience :: System Administrators
Classifier: License :: OSI Approved :: MIT License
Classifier: Operating System :: OS Independent
Classifier: Programming Language :: Python :: 3 :: Only
Classifier: Topic :: Database
Classifier: Topic :: Software Development
Classifier: Topic :: System
Classifier: Topic :: Terminals
Requires-Python: >=3
